pantos/alembic.ini
pantos/validator-node-config.env
pantos/validator-node-config.yml
pantos/validatornode/__init__.py
pantos/validatornode/__main__.py
pantos/validatornode/application.py
pantos/validatornode/blockchains/__init__.py
pantos/validatornode/blockchains/avalanche.py
pantos/validatornode/blockchains/base.py
pantos/validatornode/blockchains/bnbchain.py
pantos/validatornode/blockchains/celo.py
pantos/validatornode/blockchains/cronos.py
pantos/validatornode/blockchains/ethereum.py
pantos/validatornode/blockchains/factory.py
pantos/validatornode/blockchains/polygon.py
pantos/validatornode/blockchains/solana.py
pantos/validatornode/blockchains/sonic.py
pantos/validatornode/business/__init__.py
pantos/validatornode/business/base.py
pantos/validatornode/business/signatures.py
pantos/validatornode/business/transfers.py
pantos/validatornode/celery.py
pantos/validatornode/configuration.py
pantos/validatornode/database/__init__.py
pantos/validatornode/database/access.py
pantos/validatornode/database/enums.py
pantos/validatornode/database/exceptions.py
pantos/validatornode/database/migrations/README
pantos/validatornode/database/migrations/__init__.py
pantos/validatornode/database/migrations/env.py
pantos/validatornode/database/migrations/script.py.mako
pantos/validatornode/database/migrations/versions/2b93b957d8a4_drop_blockchain_id_check_constraint.py
pantos/validatornode/database/migrations/versions/536e50b24e1f_validator_nonce_not_nullable.py
pantos/validatornode/database/migrations/versions/578d480b68dc_initial_database_schema.py
pantos/validatornode/database/migrations/versions/__init__.py
pantos/validatornode/database/migrations/versions/d10f1f88af0f_create_validator_nodes_and_signatures.py
pantos/validatornode/database/migrations/versions/e648dd961dfc_unique_blockchain_nonce_constraint.py
pantos/validatornode/database/models.py
pantos/validatornode/entities.py
pantos/validatornode/exceptions.py
pantos/validatornode/monitor.py
pantos/validatornode/protocol.py
pantos_validator_node-2.2.0.dist-info/LICENSE.md
pantos_validator_node-2.2.0.dist-info/WHEEL
pantos_validator_node-2.2.0.dist-info/RECORD
pantos_validator_node-2.2.0.dist-info/METADATA
